_dot.py
dot.py
dot_py-1.5.1.dist-info/METADATA
dot_py-1.5.1.dist-info/WHEEL
dot_py-1.5.1.dist-info/entry_points.txt
dot_py-1.5.1.dist-info/licenses/LICENSE
dot_py-1.5.1.dist-info/RECORD
