Metadata-Version: 2.4
Name: dot.py
Version: 1.5.1
Summary: dot.py is a minimalist python script for managing dotfiles via symbolic links.
Project-URL: Homepage, https://github.com/vincentqb/dot.py/
Author-email: Vincent QB <vincentqb@gmail.com>
License-File: LICENSE
Classifier: License :: OSI Approved :: MIT License
Classifier: Programming Language :: Python :: 3
Requires-Python: >=3.6
Provides-Extra: dev
Requires-Dist: codespell; extra == 'dev'
Requires-Dist: coverage; extra == 'dev'
Requires-Dist: pre-commit; extra == 'dev'
Requires-Dist: pytest; extra == 'dev'
Requires-Dist: pytype; extra == 'dev'
Requires-Dist: ruff<0.5.3; (python_version == '3.6') and extra == 'dev'
Requires-Dist: ruff>=0.5.3; (python_version >= '3.7') and extra == 'dev'
